zanzipy/__init__.py
zanzipy/client.py
zanzipy/dsl/__init__.py
zanzipy/dsl/builder.py
zanzipy/engine/checker.py
zanzipy/engine/expander.py
zanzipy/engine_integration.py
zanzipy/integration/decorators.py
zanzipy/integration/flask/__init__.py
zanzipy/integration/flask/decorators.py
zanzipy/integration/flask/proxy.py
zanzipy/integration/mixins.py
zanzipy/models/__init__.py
zanzipy/models/check.py
zanzipy/models/errors.py
zanzipy/models/filter.py
zanzipy/models/id.py
zanzipy/models/identifier.py
zanzipy/models/namespace.py
zanzipy/models/object.py
zanzipy/models/relation.py
zanzipy/models/subject.py
zanzipy/models/tuple.py
zanzipy/schema/__init__.py
zanzipy/schema/namespace.py
zanzipy/schema/permissions.py
zanzipy/schema/registry.py
zanzipy/schema/relations.py
zanzipy/schema/rules.py
zanzipy/schema/subjects.py
zanzipy/storage/cache/abstract/rules.py
zanzipy/storage/cache/abstract/tuples.py
zanzipy/storage/cache/concrete/lru.py
zanzipy/storage/cache/concrete/lru_rules.py
zanzipy/storage/cache/concrete/redis.py
zanzipy/storage/cache/concrete/redis_rules.py
zanzipy/storage/common.py
zanzipy/storage/repos/__init__.py
zanzipy/storage/repos/abstract/__init__.py
zanzipy/storage/repos/abstract/base.py
zanzipy/storage/repos/abstract/relations.py
zanzipy/storage/repos/concrete/__init__.py
zanzipy/storage/repos/concrete/memory/relations.py
zanzipy/storage/repos/concrete/sqlalchemy/__init__.py
zanzipy/storage/repos/concrete/sqlalchemy/relations.py
zanzipy/storage/repos/concrete/sqlite/__init__.py
zanzipy/storage/repos/concrete/sqlite/relations.py
zanzipy/storage/repos/decorators/cached_relations.py
zanzipy-0.1.3.dist-info/WHEEL
zanzipy-0.1.3.dist-info/METADATA
zanzipy-0.1.3.dist-info/RECORD
