Metadata-Version: 2.3
Name: zanzipy
Version: 0.1.3
Summary: Building blocks for zanzibar style ReBAC
Keywords: rebac,zanzibar,authorization,acl,relations
Author: Tyler Chambers
License:                                  Apache License
Classifier: Programming Language :: Python :: 3
Classifier: Programming Language :: Python :: 3.14
Classifier: License :: OSI Approved :: Apache Software License
Classifier: Intended Audience :: Developers
Classifier: Topic :: Security
Classifier: Typing :: Typed
Requires-Dist: sqlalchemy>=2,<3 ; extra == 'sqlalchemy'
Requires-Python: >=3.14
Project-URL: Homepage, https://gitlab.com/tylerchambers/zanzipy
Project-URL: Issues, https://gitlab.com/tylerchambers/zanzipy/-/issues
Project-URL: Repository, https://gitlab.com/tylerchambers/zanzipy
Provides-Extra: sqlalchemy
Provides-Extra: sqlite
